zeus_py/__init__.py
zeus_py/core.py
zeus_py/course.py
zeus_py/course_type.py
zeus_py/group.py
zeus_py-2.0.0.dist-info/METADATA
zeus_py-2.0.0.dist-info/WHEEL
zeus_py-2.0.0.dist-info/top_level.txt
zeus_py-2.0.0.dist-info/RECORD
