Metadata-Version: 2.2
Name: zeus_py
Version: 2.0.0
Summary: A simple wrapper written in Python for the Zeus API.
Home-page: https://github.com/EPI-Companion/zeus.py
Author: C&S
Classifier: Programming Language :: Python :: 3
Requires-Python: ==3.12.*
Requires-Dist: httpx==0.28.1
Requires-Dist: requests==2.32.3
Dynamic: author
Dynamic: classifier
Dynamic: description
Dynamic: description-content-type
Dynamic: home-page
Dynamic: requires-dist
Dynamic: requires-python
Dynamic: summary
